gflake/__init__.py
gflake/cli.py
gflake/gflake_runner.py
gflake/menu_system.py
gflake/test_discovery.py
gflake/test_runner.py
gflake/utils.py
gflake-0.1.3.dist-info/LICENSE
gflake-0.1.3.dist-info/METADATA
gflake-0.1.3.dist-info/WHEEL
gflake-0.1.3.dist-info/entry_points.txt
gflake-0.1.3.dist-info/RECORD
