Metadata-Version: 2.3
Name: gflake
Version: 0.1.3
Summary: A CLI tool to automatically discover and repeatedly run Google Test (gtest) test cases to identify flaky tests.
Author: Deniz Ariyan
Author-email: contact@denizariyan.com
Requires-Python: >=3.10
Classifier: Programming Language :: Python :: 3
Classifier: Programming Language :: Python :: 3.10
Classifier: Programming Language :: Python :: 3.11
Classifier: Programming Language :: Python :: 3.12
Classifier: Programming Language :: Python :: 3.13
Provides-Extra: dev
Requires-Dist: pytest (>=8.0.0) ; extra == "dev"
Requires-Dist: pytest-cov (>=6.0.0) ; extra == "dev"
Requires-Dist: questionary (>=2.0.0)
Requires-Dist: rich (>=14.0.0)
Requires-Dist: ruff (>=0.12.0) ; extra == "dev"
Requires-Dist: typer[all] (>=0.16.0)
Project-URL: Homepage, https://github.com/denizariyan/gflake
Project-URL: Issues, https://github.com/denizariyan/gflake/issues
Project-URL: Repository, https://github.com/denizariyan/gflake.git
